engines/__init__.py
engines/__version__.py
engines/engines.py
engines-0.0.1.dist-info/METADATA
engines-0.0.1.dist-info/WHEEL
engines-0.0.1.dist-info/top_level.txt
engines-0.0.1.dist-info/RECORD
