Metadata-Version: 2.1
Name: engines
Version: 0.0.1
Summary: An SDK for interacting with Primer Engines
Home-page: UNKNOWN
Author: Primer AI
Author-email: primer@primer.ai
License: UNKNOWN
Platform: UNKNOWN
Classifier: Programming Language :: Python :: 3
Classifier: License :: OSI Approved :: MIT License
Classifier: Operating System :: OS Independent
Requires-Dist: certifi (==2021.5.30)
Requires-Dist: chardet (==4.0.0)
Requires-Dist: idna (==2.10)
Requires-Dist: requests (==2.25.1)
Requires-Dist: urllib3 (==1.26.6)
